smartmeter_datacollector/__init__.py
smartmeter_datacollector/__main__.py
smartmeter_datacollector/app.py
smartmeter_datacollector/collector.py
smartmeter_datacollector/config.py
smartmeter_datacollector/factory.py
smartmeter_datacollector/sinks/__init__.py
smartmeter_datacollector/sinks/data_sink.py
smartmeter_datacollector/sinks/logger_sink.py
smartmeter_datacollector/sinks/mqtt_sink.py
smartmeter_datacollector/smartmeter/__init__.py
smartmeter_datacollector/smartmeter/cosem.py
smartmeter_datacollector/smartmeter/hdlc_dlms_parser.py
smartmeter_datacollector/smartmeter/iskraam550.py
smartmeter_datacollector/smartmeter/kamstrup_han.py
smartmeter_datacollector/smartmeter/lge360.py
smartmeter_datacollector/smartmeter/lge450.py
smartmeter_datacollector/smartmeter/lge570.py
smartmeter_datacollector/smartmeter/meter.py
smartmeter_datacollector/smartmeter/meter_data.py
smartmeter_datacollector/smartmeter/obis.py
smartmeter_datacollector/smartmeter/reader.py
smartmeter_datacollector/smartmeter/serial_reader.py
smartmeter_datacollector/smartmeter/siemens_td3511.py
smartmeter_datacollector-1.3.0.dist-info/LICENSE
smartmeter_datacollector-1.3.0.dist-info/LICENSES/README.md
smartmeter_datacollector-1.3.0.dist-info/METADATA
smartmeter_datacollector-1.3.0.dist-info/WHEEL
smartmeter_datacollector-1.3.0.dist-info/entry_points.txt
smartmeter_datacollector-1.3.0.dist-info/RECORD
