Metadata-Version: 2.3
Name: smartmeter-datacollector
Version: 1.3.0
Summary: Smart Meter Data Collector
License: GPL-2.0-only
Author: Supercomputing Systems AG
Author-email: info@scs.ch
Maintainer: Supercomputing Systems AG
Maintainer-email: info@scs.ch
Requires-Python: >=3.10,<4.0
Classifier: Development Status :: 5 - Production/Stable
Classifier: License :: OSI Approved :: GNU General Public License v2 (GPLv2)
Classifier: Programming Language :: Python :: 3
Classifier: Programming Language :: Python :: 3.10
Classifier: Programming Language :: Python :: 3.11
Classifier: Programming Language :: Python :: 3.12
Classifier: Programming Language :: Python :: 3.13
Classifier: Programming Language :: Python :: 3.14
Classifier: Typing :: Typed
Requires-Dist: aiomqtt (>=2.4,<3.0)
Requires-Dist: aioserial (>=1.3,<2.0)
Requires-Dist: gurux-dlms (>=1.0.181,<2.0.0)
Project-URL: Bug Reports, https://github.com/scs/smartmeter-datacollector/issues
Project-URL: Documentation, https://github.com/scs/smartmeter-datacollector/wiki
Project-URL: Homepage, https://github.com/scs/smartmeter-datacollector
Project-URL: Pull Requests, https://github.com/scs/smartmeter-datacollector/pulls
Project-URL: Repository, https://github.com/scs/smartmeter-datacollector
Project-URL: SCS, https://www.scs.ch
